{
  "address1": "8020 Katy Freeway",
  "city": "Houston",
  "state": "TX",
  "zip": "77024-1908",
  "country": "United States",
  "phone": "713 570 3000",
  "fax": "713 570 3100",
  "website": "https://www.crowncastle.com",
  "industry": "REIT\u2014Specialty",
  "industryDisp": "REIT\u2014Specialty",
  "sector": "Real Estate",
  "sectorDisp": "Real Estate",
  "longBusinessSummary": "Crown Castle owns, operates and leases more than 40,000 cell towers and approximately 85,000 route miles of fiber supporting small cells and fiber solutions across every major U.S. market. This nationwide portfolio of communications infrastructure connects cities and communities to essential data, technology and wireless service - bringing information, ideas and innovations to the people and businesses that need them.",
  "fullTimeEmployees": 5000,
  "companyOfficers": [
    {
      "maxAge": 1,
      "name": "Mr. Jay A. Brown",
      "age": 49,
      "title": "Pres, CEO & Director",
      "yearBorn": 1973,
      "fiscalYear": 2022,
      "totalPay": 3710801,
      "exercisedValue": 0,
      "unexercisedValue": 0
    },
    {
      "maxAge": 1,
      "name": "Mr. Daniel K. Schlanger",
      "age": 48,
      "title": "Exec. VP & CFO",
      "yearBorn": 1974,
      "fiscalYear": 2022,
      "totalPay": 1543815,
      "exercisedValue": 0,
      "unexercisedValue": 0
    },
    {
      "maxAge": 1,
      "name": "Mr. Michael Joseph Kavanagh",
      "age": 54,
      "title": "Exec. VP of Sales & Chief Commercial Officer",
      "yearBorn": 1968,
      "fiscalYear": 2022,
      "totalPay": 1601097,
      "exercisedValue": 0,
      "unexercisedValue": 0
    },
    {
      "maxAge": 1,
      "name": "Mr. Christopher D. Levendos",
      "age": 54,
      "title": "Exec. VP & COO of Fiber",
      "yearBorn": 1968,
      "fiscalYear": 2022,
      "totalPay": 1313441,
      "exercisedValue": 0,
      "unexercisedValue": 0
    },
    {
      "maxAge": 1,
      "name": "Ms. Catherine  Piche",
      "age": 51,
      "title": "Exec. VP & COO of Towers",
      "yearBorn": 1971,
      "fiscalYear": 2022,
      "totalPay": 1310284,
      "exercisedValue": 0,
      "unexercisedValue": 0
    },
    {
      "maxAge": 1,
      "name": "Mr. Robert Sean Collins",
      "age": 55,
      "title": "Principal Accounting Officer, VP & Controller",
      "yearBorn": 1967,
      "exercisedValue": 0,
      "unexercisedValue": 0
    },
    {
      "maxAge": 1,
      "name": "Kris  Hinson",
      "title": "VP of Corp. Fin. & Treasurer",
      "exercisedValue": 0,
      "unexercisedValue": 0
    },
    {
      "maxAge": 1,
      "name": "Mr. Edward B. Adams Jr.",
      "age": 53,
      "title": "Exec. VP & Gen. Counsel",
      "yearBorn": 1969,
      "exercisedValue": 0,
      "unexercisedValue": 0
    },
    {
      "maxAge": 1,
      "name": "Ms. Fiona  McKone",
      "title": "VP of Communications & Marketing",
      "exercisedValue": 0,
      "unexercisedValue": 0
    },
    {
      "maxAge": 1,
      "name": "Mr. Philip M. Kelley",
      "age": 49,
      "title": "Exec. VP of Corp. Devel. & Strategy",
      "yearBorn": 1973,
      "fiscalYear": 2008,
      "exercisedValue": 0,
      "unexercisedValue": 0
    }
  ],
  "auditRisk": 2,
  "boardRisk": 2,
  "compensationRisk": 2,
  "shareHolderRightsRisk": 8,
  "overallRisk": 2,
  "governanceEpochDate": 1693526400,
  "compensationAsOfEpochDate": 1672444800,
  "maxAge": 86400,
  "priceHint": 2,
  "previousClose": 92.9,
  "open": 93.5,
  "dayLow": 91.6222,
  "dayHigh": 93.0873,
  "regularMarketPreviousClose": 92.9,
  "regularMarketOpen": 93.5,
  "regularMarketDayLow": 91.6222,
  "regularMarketDayHigh": 93.0873,
  "dividendRate": 6.26,
  "dividendYield": 0.0674,
  "exDividendDate": 1694649600,
  "payoutRatio": 1.5687,
  "fiveYearAvgDividendYield": 3.47,
  "beta": 0.65076,
  "trailingPE": 23.404581,
  "forwardPE": 28.654207,
  "volume": 3532375,
  "regularMarketVolume": 3532375,
  "averageVolume": 3130138,
  "averageVolume10days": 3340830,
  "averageDailyVolume10Day": 3340830,
  "bid": 91.86,
  "ask": 91.79,
  "bidSize": 800,
  "askSize": 800,
  "marketCap": 39889797120,
  "fiftyTwoWeekLow": 91.6222,
  "fiftyTwoWeekHigh": 153.98,
  "priceToSalesTrailing12Months": 5.5789924,
  "fiftyDayAverage": 103.292,
  "twoHundredDayAverage": 122.6885,
  "trailingAnnualDividendRate": 6.165,
  "trailingAnnualDividendYield": 0.06636168,
  "currency": "USD",
  "enterpriseValue": 68522737664,
  "profitMargins": 0.23874001,
  "floatShares": 431332343,
  "sharesOutstanding": 433679008,
  "sharesShort": 4783136,
  "sharesShortPriorMonth": 4857292,
  "sharesShortPreviousMonthDate": 1690761600,
  "dateShortInterest": 1693440000,
  "sharesPercentSharesOut": 0.011,
  "heldPercentInsiders": 0.00348,
  "heldPercentInstitutions": 0.92638,
  "shortRatio": 1.7,
  "shortPercentOfFloat": 0.0128,
  "impliedSharesOutstanding": 433679008,
  "bookValue": 16.235,
  "priceToBook": 5.6655374,
  "lastFiscalYearEnd": 1672444800,
  "nextFiscalYearEnd": 1703980800,
  "mostRecentQuarter": 1688083200,
  "earningsQuarterlyGrowth": 0.081,
  "netIncomeToCommon": 1707000064,
  "trailingEps": 3.93,
  "forwardEps": 3.21,
  "pegRatio": -5.04,
  "enterpriseToRevenue": 9.584,
  "enterpriseToEbitda": 16.195,
  "52WeekChange": -0.38378882,
  "SandP52WeekChange": 0.18466556,
  "lastDividendValue": 1.565,
  "lastDividendDate": 1694649600,
  "exchange": "NYQ",
  "quoteType": "EQUITY",
  "symbol": "CCI",
  "underlyingSymbol": "CCI",
  "shortName": "Crown Castle Inc.",
  "longName": "Crown Castle Inc.",
  "firstTradeDateEpochUtc": 903447000,
  "timeZoneFullName": "America/New_York",
  "timeZoneShortName": "EDT",
  "uuid": "9a57ae65-7908-3165-b69c-57474f0c4bfe",
  "messageBoardId": "finmb_27198",
  "gmtOffSetMilliseconds": -14400000,
  "currentPrice": 91.98,
  "targetHighPrice": 151.0,
  "targetLowPrice": 91.0,
  "targetMeanPrice": 123.25,
  "targetMedianPrice": 122.5,
  "recommendationMean": 2.6,
  "recommendationKey": "hold",
  "numberOfAnalystOpinions": 16,
  "totalCash": 276000000,
  "totalCashPerShare": 0.636,
  "ebitda": 4231000064,
  "totalDebt": 28509999104,
  "quickRatio": 0.326,
  "currentRatio": 0.495,
  "totalRevenue": 7150000128,
  "debtToEquity": 404.627,
  "revenuePerShare": 16.513,
  "returnOnAssets": 0.04074,
  "returnOnEquity": 0.22902,
  "grossProfits": 4918000000,
  "freeCashflow": 1578499968,
  "operatingCashflow": 3265999872,
  "earningsGrowth": 0.081,
  "revenueGrowth": 0.077,
  "grossMargins": 0.70825,
  "ebitdaMargins": 0.59174997,
  "operatingMargins": 0.35580003,
  "financialCurrency": "USD",
  "trailingPegRatio": 3.0599
}