{
  "address1": "1100 Park Place",
  "address2": "Suite 200",
  "city": "San Mateo",
  "state": "CA",
  "zip": "94403-7107",
  "country": "United States",
  "phone": "650 655 7800",
  "fax": "650 655 7810",
  "website": "https://www.essexapartmenthomes.com",
  "industry": "REIT\u2014Residential",
  "industryDisp": "REIT\u2014Residential",
  "sector": "Real Estate",
  "sectorDisp": "Real Estate",
  "longBusinessSummary": "Essex Property Trust, Inc., an S&P 500 company, is a fully integrated real estate investment trust (REIT) that acquires, develops, redevelops, and manages multifamily residential properties in selected West Coast markets. Essex currently has ownership interests in 252 apartment communities comprising approximately 62,000 apartment homes with an additional property in active development.",
  "fullTimeEmployees": 1770,
  "companyOfficers": [
    {
      "maxAge": 1,
      "name": "Ms. Angela L. Kleiman",
      "age": 51,
      "title": "Pres, CEO & Director",
      "yearBorn": 1971,
      "fiscalYear": 2022,
      "totalPay": 2120958,
      "exercisedValue": 630900,
      "unexercisedValue": 0
    },
    {
      "maxAge": 1,
      "name": "Ms. Barbara M. Pak CFA",
      "age": 44,
      "title": "Exec. VP & CFO",
      "yearBorn": 1978,
      "fiscalYear": 2022,
      "totalPay": 1969248,
      "exercisedValue": 0,
      "unexercisedValue": 0
    },
    {
      "maxAge": 1,
      "name": "Ms. Anne M. Morrison",
      "age": 41,
      "title": "Sr. VP, Chief Compliance Officer, Gen. Counsel & Sec.",
      "yearBorn": 1981,
      "fiscalYear": 2022,
      "totalPay": 1053507,
      "exercisedValue": 0,
      "unexercisedValue": 0
    },
    {
      "maxAge": 1,
      "name": "Mr. Rylan  Burns",
      "title": "Sr. VP of Investment Strategy",
      "exercisedValue": 0,
      "unexercisedValue": 0
    },
    {
      "maxAge": 1,
      "name": "Mr. John  Farias",
      "age": 53,
      "title": "Sr. VP & Chief Accounting Officer",
      "yearBorn": 1969,
      "exercisedValue": 0,
      "unexercisedValue": 0
    },
    {
      "maxAge": 1,
      "name": "Sudarshana  Rangachary",
      "title": "Sr. VP of HR",
      "exercisedValue": 0,
      "unexercisedValue": 0
    },
    {
      "maxAge": 1,
      "name": "Dmitry  Taraschansky",
      "title": "Sr. VP of Acquisitions & Investments",
      "exercisedValue": 0,
      "unexercisedValue": 0
    },
    {
      "maxAge": 1,
      "name": "Jessica  Anderson",
      "title": "Sr. VP of Operations",
      "exercisedValue": 0,
      "unexercisedValue": 0
    },
    {
      "maxAge": 1,
      "name": "Mr. Paul Burton Morgan",
      "title": "Sr. VP of Portfolio Strategy & Analytics",
      "exercisedValue": 0,
      "unexercisedValue": 0
    }
  ],
  "auditRisk": 1,
  "boardRisk": 9,
  "compensationRisk": 2,
  "shareHolderRightsRisk": 7,
  "overallRisk": 4,
  "governanceEpochDate": 1693526400,
  "compensationAsOfEpochDate": 1672444800,
  "maxAge": 86400,
  "priceHint": 2,
  "previousClose": 219.08,
  "open": 218.76,
  "dayLow": 215.29,
  "dayHigh": 219.435,
  "regularMarketPreviousClose": 219.08,
  "regularMarketOpen": 218.76,
  "regularMarketDayLow": 215.29,
  "regularMarketDayHigh": 219.435,
  "dividendRate": 9.24,
  "dividendYield": 0.0422,
  "exDividendDate": 1695859200,
  "payoutRatio": 1.0987,
  "fiveYearAvgDividendYield": 3.11,
  "beta": 0.784578,
  "trailingPE": 26.233576,
  "forwardPE": 36.0602,
  "volume": 370442,
  "regularMarketVolume": 370442,
  "averageVolume": 405817,
  "averageVolume10days": 461100,
  "averageDailyVolume10Day": 461100,
  "bid": 210.85,
  "ask": 215.49,
  "bidSize": 900,
  "askSize": 800,
  "marketCap": 14327855104,
  "fiftyTwoWeekLow": 195.03,
  "fiftyTwoWeekHigh": 249.67,
  "priceToSalesTrailing12Months": 8.479215,
  "fiftyDayAverage": 236.7526,
  "twoHundredDayAverage": 223.85315,
  "trailingAnnualDividendRate": 9.02,
  "trailingAnnualDividendYield": 0.041172177,
  "currency": "USD",
  "enterpriseValue": 20208076800,
  "profitMargins": 0.31434,
  "floatShares": 63696795,
  "sharesOutstanding": 64183300,
  "sharesShort": 1218554,
  "sharesShortPriorMonth": 1358827,
  "sharesShortPreviousMonthDate": 1690761600,
  "dateShortInterest": 1693440000,
  "sharesPercentSharesOut": 0.019,
  "heldPercentInsiders": 0.01197,
  "heldPercentInstitutions": 0.98262,
  "shortRatio": 3.29,
  "shortPercentOfFloat": 0.0312,
  "impliedSharesOutstanding": 66443400,
  "bookValue": 87.021,
  "priceToBook": 2.4780223,
  "lastFiscalYearEnd": 1672444800,
  "nextFiscalYearEnd": 1703980800,
  "mostRecentQuarter": 1688083200,
  "earningsQuarterlyGrowth": 0.746,
  "netIncomeToCommon": 531159008,
  "trailingEps": 8.22,
  "forwardEps": 5.98,
  "pegRatio": 4.04,
  "enterpriseToRevenue": 11.959,
  "enterpriseToEbitda": 18.264,
  "52WeekChange": -0.090878904,
  "SandP52WeekChange": 0.18466556,
  "lastDividendValue": 2.31,
  "lastDividendDate": 1687996800,
  "exchange": "NYQ",
  "quoteType": "EQUITY",
  "symbol": "ESS",
  "underlyingSymbol": "ESS",
  "shortName": "Essex Property Trust, Inc.",
  "longName": "Essex Property Trust, Inc.",
  "firstTradeDateEpochUtc": 770995800,
  "timeZoneFullName": "America/New_York",
  "timeZoneShortName": "EDT",
  "uuid": "ffea021a-2ef0-3d50-98bb-8ae2f868d64e",
  "messageBoardId": "finmb_332646",
  "gmtOffSetMilliseconds": -14400000,
  "currentPrice": 215.64,
  "targetHighPrice": 282.0,
  "targetLowPrice": 204.0,
  "targetMeanPrice": 249.37,
  "targetMedianPrice": 248.0,
  "recommendationMean": 3.0,
  "recommendationKey": "hold",
  "numberOfAnalystOpinions": 19,
  "totalCash": 70049000,
  "totalCashPerShare": 1.091,
  "ebitda": 1106448000,
  "totalDebt": 6008764928,
  "quickRatio": 0.254,
  "currentRatio": 0.745,
  "totalRevenue": 1689762048,
  "debtToEquity": 103.718,
  "revenuePerShare": 26.155,
  "returnOnAssets": 0.02833,
  "returnOnEquity": 0.094689995,
  "grossProfits": 1122739000,
  "freeCashflow": 787082112,
  "operatingCashflow": 954430976,
  "earningsGrowth": 0.782,
  "revenueGrowth": 0.094,
  "grossMargins": 0.6905,
  "ebitdaMargins": 0.65480006,
  "operatingMargins": 0.33266,
  "financialCurrency": "USD",
  "trailingPegRatio": 2.778
}