{
  "address1": "55 Water Street",
  "city": "New York",
  "state": "NY",
  "zip": "10041",
  "country": "United States",
  "phone": "212 438 1000",
  "website": "https://www.spglobal.com",
  "industry": "Financial Data & Stock Exchanges",
  "industryDisp": "Financial Data & Stock Exchanges",
  "sector": "Financial Services",
  "sectorDisp": "Financial Services",
  "longBusinessSummary": "S&P Global Inc., together with its subsidiaries, provides credit ratings, benchmarks, analytics, and workflow solutions in the global capital, commodity, and automotive markets. It operates through six segments: S&P Global Ratings, S&P Dow Jones Indices, S&P Global Commodity Insights, S&P Global Market Intelligence, S&P Global Mobility, and S&P Global Engineering Solutions. The S&P Global Ratings segment operates as an independent provider of credit ratings, research, and analytics, offering investors and other market participants information, ratings, and benchmarks. The S&P Dow Jones Indices segment is an index provider that maintains various valuation and index benchmarks for investment advisors, wealth managers, and institutional investors. The S&P Global Commodity Insights segment provides information and benchmark prices for the commodity and energy markets. The S&P Global Market Intelligence segment offers multi-asset-class data and analytics integrated with purpose-built workflow solutions. This segment offers Desktop, a product suite that provides data, analytics, and third-party research; Data and Advisory Solutions for research, reference data, market data, derived analytics, and valuation services; Enterprise Solutions, software and workflow solutions; and Credit & Risk Solutions for selling Ratings' credit ratings and related data and research. The S&P Global Mobility segment provides solutions serving the full automotive value chain, including vehicle manufacturers (OEMs), automotive suppliers, mobility service providers, retailers, consumers, and finance and insurance companies. The S&P Global Engineering Solutions segment offers engineering standards and related technical knowledge, including product design to provide information and insight to design products, optimize engineering projects and outcomes, solve technical problems, and address complex supply chain issues. S&P Global Inc. was founded in 1860 and is headquartered in New York, New York.",
  "fullTimeEmployees": 39660,
  "companyOfficers": [
    {
      "maxAge": 1,
      "name": "Mr. Douglas L. Peterson M.B.A.",
      "age": 64,
      "title": "Pres, CEO & Exec. Director",
      "yearBorn": 1958,
      "fiscalYear": 2022,
      "totalPay": 4837515,
      "exercisedValue": 0,
      "unexercisedValue": 13191798
    },
    {
      "maxAge": 1,
      "name": "Ms. Martina L. Cheung",
      "age": 46,
      "title": "Pres of S&P Global Ratings, Inc. & Exec. Sponsor of S&P Global Sustainable1",
      "yearBorn": 1976,
      "fiscalYear": 2022,
      "totalPay": 1971817,
      "exercisedValue": 0,
      "unexercisedValue": 0
    },
    {
      "maxAge": 1,
      "name": "Mr. Daniel Eugene Draper CAIA, CFA, CMT, FRM",
      "age": 54,
      "title": "Chief Exec. Officer of S&P Dow Jones Indices LLC",
      "yearBorn": 1968,
      "fiscalYear": 2022,
      "totalPay": 3766904,
      "exercisedValue": 0,
      "unexercisedValue": 0
    },
    {
      "maxAge": 1,
      "name": "Mr. Adam J. Kansler",
      "age": 52,
      "title": "Pres of S&P Global Market Intelligence, Inc.",
      "yearBorn": 1970,
      "fiscalYear": 2022,
      "totalPay": 2163243,
      "exercisedValue": 0,
      "unexercisedValue": 0
    },
    {
      "maxAge": 1,
      "name": "Mr. Ewout Lucien Steenbergen",
      "age": 53,
      "title": "Exec. VP & CFO",
      "yearBorn": 1969,
      "fiscalYear": 2022,
      "totalPay": 2363330,
      "exercisedValue": 0,
      "unexercisedValue": 0
    },
    {
      "maxAge": 1,
      "name": "Mr. Saugata  Saha",
      "age": 46,
      "title": "Pres of S&P Global Commodity Insights",
      "yearBorn": 1976,
      "fiscalYear": 2021,
      "exercisedValue": 0,
      "unexercisedValue": 0
    },
    {
      "maxAge": 1,
      "name": "Mr. Sitarama Swamy Kocherlakota",
      "age": 55,
      "title": "Exec. VP & Chief Information Officer",
      "yearBorn": 1967,
      "exercisedValue": 0,
      "unexercisedValue": 0
    },
    {
      "maxAge": 1,
      "name": "Mr. Steven  Kemps",
      "age": 57,
      "title": "Exec. VP & Chief Legal Officer",
      "yearBorn": 1965,
      "fiscalYear": 2016,
      "exercisedValue": 0,
      "unexercisedValue": 0
    },
    {
      "maxAge": 1,
      "name": "Ms. Dimitra  Manis",
      "age": 55,
      "title": "Exec. VP & Chief Purpose Officer",
      "yearBorn": 1967,
      "exercisedValue": 0,
      "unexercisedValue": 0
    },
    {
      "maxAge": 1,
      "name": "Mr. Edouard  Tavernier",
      "age": 48,
      "title": "Pres of S&P Global Mobility",
      "yearBorn": 1974,
      "exercisedValue": 0,
      "unexercisedValue": 0
    }
  ],
  "auditRisk": 1,
  "boardRisk": 3,
  "compensationRisk": 7,
  "shareHolderRightsRisk": 4,
  "overallRisk": 2,
  "governanceEpochDate": 1693526400,
  "compensationAsOfEpochDate": 1672444800,
  "maxAge": 86400,
  "priceHint": 2,
  "previousClose": 372.31,
  "open": 372.57,
  "dayLow": 371.115,
  "dayHigh": 375.9,
  "regularMarketPreviousClose": 372.31,
  "regularMarketOpen": 372.57,
  "regularMarketDayLow": 371.115,
  "regularMarketDayHigh": 375.9,
  "dividendRate": 3.6,
  "dividendYield": 0.0097,
  "exDividendDate": 1692921600,
  "payoutRatio": 0.493,
  "fiveYearAvgDividendYield": 0.86,
  "beta": 1.121715,
  "trailingPE": 52.277073,
  "forwardPE": 25.704702,
  "volume": 1159277,
  "regularMarketVolume": 1159277,
  "averageVolume": 1137864,
  "averageVolume10days": 1012250,
  "averageDailyVolume10Day": 1012250,
  "bid": 364.64,
  "ask": 372.99,
  "bidSize": 900,
  "askSize": 900,
  "marketCap": 118271762432,
  "fiftyTwoWeekLow": 279.32,
  "fiftyTwoWeekHigh": 428.65,
  "priceToSalesTrailing12Months": 9.807759,
  "fiftyDayAverage": 395.596,
  "twoHundredDayAverage": 367.70825,
  "trailingAnnualDividendRate": 3.5,
  "trailingAnnualDividendYield": 0.009400768,
  "currency": "USD",
  "enterpriseValue": 132672045056,
  "profitMargins": 0.19454001,
  "floatShares": 317684516,
  "sharesOutstanding": 318200000,
  "sharesShort": 3241998,
  "sharesShortPriorMonth": 3584178,
  "sharesShortPreviousMonthDate": 1690761600,
  "dateShortInterest": 1693440000,
  "sharesPercentSharesOut": 0.010199999,
  "heldPercentInsiders": 0.002,
  "heldPercentInstitutions": 0.89871,
  "shortRatio": 3.06,
  "shortPercentOfFloat": 0.010199999,
  "impliedSharesOutstanding": 318200000,
  "bookValue": 111.464,
  "priceToBook": 3.3346193,
  "lastFiscalYearEnd": 1672444800,
  "nextFiscalYearEnd": 1703980800,
  "mostRecentQuarter": 1688083200,
  "earningsQuarterlyGrowth": -0.474,
  "netIncomeToCommon": 2345999872,
  "trailingEps": 7.11,
  "forwardEps": 14.46,
  "pegRatio": 2.23,
  "lastSplitFactor": "2:1",
  "lastSplitDate": 1116374400,
  "enterpriseToRevenue": 11.002,
  "enterpriseToEbitda": 24.61,
  "52WeekChange": 0.18032527,
  "SandP52WeekChange": 0.18466556,
  "lastDividendValue": 0.9,
  "lastDividendDate": 1692921600,
  "exchange": "NYQ",
  "quoteType": "EQUITY",
  "symbol": "SPGI",
  "underlyingSymbol": "SPGI",
  "shortName": "S&P Global Inc.",
  "longName": "S&P Global Inc.",
  "firstTradeDateEpochUtc": 99153000,
  "timeZoneFullName": "America/New_York",
  "timeZoneShortName": "EDT",
  "uuid": "4ee881d1-e561-3ba4-9941-3a51f942bca8",
  "messageBoardId": "finmb_21719",
  "gmtOffSetMilliseconds": -14400000,
  "currentPrice": 371.69,
  "targetHighPrice": 485.0,
  "targetLowPrice": 398.0,
  "targetMeanPrice": 447.95,
  "targetMedianPrice": 452.0,
  "recommendationMean": 1.7,
  "recommendationKey": "buy",
  "numberOfAnalystOpinions": 20,
  "totalCash": 1560999936,
  "totalCashPerShare": 4.906,
  "ebitda": 5391000064,
  "totalDebt": 12163000320,
  "quickRatio": 0.681,
  "currentRatio": 0.783,
  "totalRevenue": 12058999808,
  "debtToEquity": 31.132,
  "revenuePerShare": 37.259,
  "returnOnAssets": 0.04247,
  "returnOnEquity": 0.06369,
  "grossProfits": 7415000000,
  "freeCashflow": 3429125120,
  "operatingCashflow": 3289999872,
  "earningsGrowth": -0.441,
  "revenueGrowth": 0.036,
  "grossMargins": 0.65801,
  "ebitdaMargins": 0.44705,
  "operatingMargins": 0.35227,
  "financialCurrency": "USD",
  "trailingPegRatio": 2.1362
}